tex4svg.py
tex4svg-0.0.2.dist-info/LICENSE
tex4svg-0.0.2.dist-info/METADATA
tex4svg-0.0.2.dist-info/WHEEL
tex4svg-0.0.2.dist-info/top_level.txt
tex4svg-0.0.2.dist-info/RECORD
